simple_stripe_client/__init__.py
simple_stripe_client/api.py
tests/__init__.py
tests/test_api.py
simple_stripe_client-0.0.2.dist-info/LICENSE
simple_stripe_client-0.0.2.dist-info/METADATA
simple_stripe_client-0.0.2.dist-info/WHEEL
simple_stripe_client-0.0.2.dist-info/top_level.txt
simple_stripe_client-0.0.2.dist-info/RECORD
