Metadata-Version: 2.1
Name: simple-stripe-client
Version: 0.0.2
Summary: A simple lightweight api client for awesome stripe
Home-page: https://github.com/raigad/simple_stripe_client
Author: Rohit Deshmukh
Author-email: raigad1630@gmail.com
Maintainer: Rohit Deshmukh
Maintainer-email: raigad1630@gmail.com
License: MIT
Project-URL: Documentation, https://github.com/raigad/simple-stripe-client
Project-URL: Bug Tracker, https://github.com/raigad/simple-stripe-client/issues
Project-URL: Source Code, https://github.com/raigad/simple-stripe-client
Keywords: stripe,api,payments,stripe client
Platform: UNKNOWN
Classifier: Development Status :: 5 - Production/Stable
Classifier: Intended Audience :: Developers
Classifier: Natural Language :: English
Classifier: Programming Language :: Python
Classifier: Programming Language :: Python :: 2
Classifier: Programming Language :: Python :: 2.7
Classifier: Programming Language :: Python :: 3
Classifier: Programming Language :: Python :: 3.4
Classifier: Programming Language :: Python :: 3.5
Classifier: Programming Language :: Python :: 3.6
Classifier: Programming Language :: Python :: 3.7
Classifier: Programming Language :: Python :: Implementation :: PyPy
Classifier: Topic :: Software Development :: Libraries :: Python Modules
Classifier: License :: OSI Approved :: MIT License
Classifier: Operating System :: OS Independent
Requires-Dist: requests
